{
  "configPath": "cfg/v1_3_imagemap01.json",
  "simulationWidth": 1920,
  "simulationHeight": 1080,
  "useCamBounds": false,
  "camLiniency": 0.2,
  "simulationSpeed": 1,
  "useImageMap": true,
  "mapImagePath": "assets/spirited-away-no-face.jpg",
  "mapSampleDepth": 3,
  "mapSampleStep": 8,
  "mapFoodColor": "#d4c3da",
  "mapObstacleColor": "#cd4348",
  "mapNestColor": "#c79978",
  "mapColorTolerance": 300,
  "mapFoodColorTolerance": 900,
  "mapObstacleColorTolerance": null,
  "mapNestColorTolerance": null,
  "mapPaletteMinDistance": 0,
  "mapFoodUnitsPerCell": 3,
  "mapFoodDepletedColor": "#000000",
  "mapUseImageSize": true,
  "mapShowAllCells": true,
  "mapFoodErodeIterations": 0,
  "mapFoodDilateIterations": 0,
  "mapObstacleErodeIterations": 0,
  "mapObstacleDilateIterations": 1,
  "mapNestErodeIterations": 0,
  "mapNestDilateIterations": 0,
  "colorDistanceMethod": 0,
  "nestPlacementMode": 2,
  "mapShowNestMarker": true,
  "mapNestUseCellSize": true,
  "mapNestCellSizeScale": 0.9,
  "antColor": "#6b0000",
  "antSize": 12,
  "antWidth": 6,
  "pheromoneRedColor": "#fd2108",
  "pheromoneBlueColor": "#4287f5",
  "foodColor": "#2bff00",
  "foodClusterColor": "#00ff00",
  "foodClusterTextColor": "#000000",
  "obstacleColor": "#b61119",
  "nestColor": "#c70000",
  "nestTextColor": "#ffffff",
  "antCount": 200,
  "foodSpawnRadius": 50,
  "backgroundColor": "#242424",
  "obstacleLineWidth": 1,
  "obstacleQueryMethod": 0,
  "showHUD": true,
  "showObstacles": true,
  "showPheromones": false,
  "useClusteredPheromones": true,
  "useClusteredFood": false,
  "showFoodCounts": false,
  "antSpeed": 7,
  "antSight": 60,
  "antPheromoneFrequency": 3,
  "antSteeringStrength": 0.55,
  "antFoVDegrees": 135,
  "antWanderStrength": 0.2,
  "obstacleAvoidanceRandomness": 0.4,
  "obstacleAvoidStrength": 0.95,
  "wanderSpeedFactor": 0.9,
  "trailSpeedFactor": 1.1,
  "headedToFoodSpeedFactor": 1.15,
  "headedHomeSpeedFactor": 1.05,
  "obstacleSideSpeedFactor": 0.55,
  "obstacleFrontSpeedFactor": 0.2,
  "collisionTurnMinDegrees": 20,
  "collisionTurnMaxDegrees": 120,
  "collisionPauseFrames": 6,
  "boundaryNudgeDistance": 2,
  "foodPickupPauseFrames": 8,
  "foodDropPauseFrames": 6,
  "postPauseEaseFrames": 10,
  "postPauseMinSpeedFactor": 0.15,
  "pheromoneLife": 250,
  "redPheromoneLife": null,
  "bluePheromoneLife": null,
  "pheromoneLowScoreThreshold": 0.1,
  "pheromoneIgnoreProbability": 0.4,
  "pheromoneDiffusionEnabled": true,
  "pheromoneDiffusionStrength": 0.8,
  "pheromoneMaxRadius": 20,
  "pheromoneMaxIntensity": 1,
  "redPheromoneDiffusionEnabled": null,
  "redPheromoneDiffusionStrength": 1,
  "bluePheromoneDiffusionEnabled": null,
  "bluePheromoneDiffusionStrength": 1,
  "useRedPheromones": true,
  "useBluePheromones": true,
  "searchersFollowHomePheromones": false,
  "searcherHomePheromoneWeight": 1,
  "pauseWhenNoFood": true,
  "autoStartSimulation": false,
  "pheromoneClusterCellSize": 8,
  "foodClusterCellSize": 4,
  "quadTreeCapacity": 4,
  "mapFoodRenderCellsOnly": false,
  "mapFoodPlacementCellsOnly": true,
  "skipPheromoneOnCollisionPause": true
}